notify_utils/__init__.py
notify_utils/discount.py
notify_utils/models.py
notify_utils/parser.py
notify_utils/statistics.py
notify_utils/validators.py
notify_utils/notifiers/__init__.py
notify_utils/notifiers/discord_notifier.py
notify_utils/notifiers/formatters.py
notify_utils-0.0.1.dist-info/licenses/LICENSE
notify_utils-0.0.1.dist-info/METADATA
notify_utils-0.0.1.dist-info/WHEEL
notify_utils-0.0.1.dist-info/top_level.txt
notify_utils-0.0.1.dist-info/RECORD
