Metadata-Version: 2.4
Name: notify-utils
Version: 0.0.1
Summary: Biblioteca Python para parsing de preços de scraping, cálculo de descontos e análise estatística de histórico de preços.
Author-email: Naruto Uzumaki <naruto_uzumaki@gmail.com>
License: MIT
Project-URL: Homepage, https://github.com/jefersonAlbara/notify-utils
Project-URL: Repository, https://github.com/jefersonAlbara/notify-utils
Project-URL: Issues, https://github.com/jefersonAlbara/notify-utils/issues
Keywords: price-tracking,discount-calculator,web-scraping,e-commerce,price-history,discount-analysis,promotion-detection,statistics
Classifier: Development Status :: 4 - Beta
Classifier: Intended Audience :: Developers
Classifier: License :: OSI Approved :: MIT License
Classifier: Programming Language :: Python :: 3
Classifier: Programming Language :: Python :: 3.12
Classifier: Topic :: Software Development :: Libraries :: Python Modules
Classifier: Topic :: Office/Business :: Financial
Requires-Python: >=3.12
License-File: LICENSE
Requires-Dist: discord-webhook>=1.4.1
Dynamic: license-file
